module_sdstate/__init__.py
module_sdstate/lanczos_utils.py
module_sdstate/sdstate_utils.py
module_sdstate-0.2.7.dist-info/LICENSE
module_sdstate-0.2.7.dist-info/METADATA
module_sdstate-0.2.7.dist-info/WHEEL
module_sdstate-0.2.7.dist-info/RECORD
