Metadata-Version: 2.1
Name: module_sdstate
Version: 0.2.7
Summary: Implementation of Slater Determinant states as dictionaries of states and coefficient pairs. Each state is represented with an integar treated as binary, allowing applying of Excitation operators on the state efficiently. Memory-efficient implementation of Lanczos iteration for estimating Hamiltonian spectrum range.
License: MIT
Author: Linjun Wang
Requires-Python: >=3.9,<4.0
Classifier: License :: OSI Approved :: MIT License
Classifier: Programming Language :: Python :: 3
Classifier: Programming Language :: Python :: 3.9
Classifier: Programming Language :: Python :: 3.10
Classifier: Programming Language :: Python :: 3.11
Classifier: Programming Language :: Python :: 3.12
Requires-Dist: numpy (>=1.26.4,<2.0.0)
Requires-Dist: openfermion (>=1.6.1,<2.0.0)
